ibutton2uid.py
ibutton2uid-1.0.0.dist-info/DESCRIPTION.rst
ibutton2uid-1.0.0.dist-info/METADATA
ibutton2uid-1.0.0.dist-info/RECORD
ibutton2uid-1.0.0.dist-info/WHEEL
ibutton2uid-1.0.0.dist-info/metadata.json
ibutton2uid-1.0.0.dist-info/top_level.txt
